carve_exe/__init__.py
carve_exe/app.py
carve_exe/carver.py
carve_exe/filetypes/__init__.py
carve_exe/filetypes/elf.py
carve_exe/filetypes/filetype.py
carve_exe/filetypes/pe.py
carve_exe-1.0.1.dist-info/METADATA
carve_exe-1.0.1.dist-info/WHEEL
carve_exe-1.0.1.dist-info/entry_points.txt
carve_exe-1.0.1.dist-info/RECORD
