Metadata-Version: 2.1
Name: carve-exe
Version: 1.0.1
Summary: Carve Exe is a simple best effort tool to carve PE and ELF files from arbitrary, binary files (e.g. memory dumps and executables).
Home-page: https://github.com/joren485/carve-exe/
Requires-Python: >=3.12,<4.0
Classifier: Programming Language :: Python :: 3
Classifier: Programming Language :: Python :: 3.12
Requires-Dist: loguru (>=0.7.2,<0.8.0)
Requires-Dist: pefile (>=2023.2.7,<2024.0.0)
Requires-Dist: pyelftools (>=0.31,<0.32)
Requires-Dist: typer (>=0.12.3,<0.13.0)
Project-URL: Bug Tracker, https://github.com/joren485/carve-exe/issues/
Project-URL: Repository, https://github.com/joren485/carve-exe/
